jupyter_copernicus/__init__.py
jupyter_copernicus/_version.py
jupyter_copernicus/handlers.py
jupyter_copernicus/tests/__init__.py
jupyter_copernicus/tests/test_handlers.py
jupyter_copernicus-0.0.2.data/data/etc/jupyter/jupyter_notebook_config.d/jupyter_copernicus.json
jupyter_copernicus-0.0.2.data/data/etc/jupyter/jupyter_server_config.d/jupyter_copernicus.json
jupyter_copernicus-0.0.2.data/data/share/jupyter/labextensions/@datalayer/jupyter-copernicus/build_log.json
jupyter_copernicus-0.0.2.data/data/share/jupyter/labextensions/@datalayer/jupyter-copernicus/package.json
jupyter_copernicus-0.0.2.data/data/share/jupyter/labextensions/@datalayer/jupyter-copernicus/schemas/@datalayer/jupyter-copernicus/package.json.orig
jupyter_copernicus-0.0.2.data/data/share/jupyter/labextensions/@datalayer/jupyter-copernicus/schemas/@datalayer/jupyter-copernicus/plugin.json
jupyter_copernicus-0.0.2.data/data/share/jupyter/labextensions/@datalayer/jupyter-copernicus/static/design_icons_lib_index_js.8ff1c792a6eba1c03566.js
jupyter_copernicus-0.0.2.data/data/share/jupyter/labextensions/@datalayer/jupyter-copernicus/static/design_icons_lib_index_js.8ff1c792a6eba1c03566.js.map
jupyter_copernicus-0.0.2.data/data/share/jupyter/labextensions/@datalayer/jupyter-copernicus/static/lib_index_js.473808c38800f9785373.js
jupyter_copernicus-0.0.2.data/data/share/jupyter/labextensions/@datalayer/jupyter-copernicus/static/lib_index_js.473808c38800f9785373.js.map
jupyter_copernicus-0.0.2.data/data/share/jupyter/labextensions/@datalayer/jupyter-copernicus/static/remoteEntry.cbd6074894f5f65157fa.js
jupyter_copernicus-0.0.2.data/data/share/jupyter/labextensions/@datalayer/jupyter-copernicus/static/remoteEntry.cbd6074894f5f65157fa.js.map
jupyter_copernicus-0.0.2.data/data/share/jupyter/labextensions/@datalayer/jupyter-copernicus/static/style.js
jupyter_copernicus-0.0.2.data/data/share/jupyter/labextensions/@datalayer/jupyter-copernicus/static/style_index_js.cef17aad744574850369.js
jupyter_copernicus-0.0.2.dist-info/METADATA
jupyter_copernicus-0.0.2.dist-info/WHEEL
jupyter_copernicus-0.0.2.dist-info/licenses/LICENSE
jupyter_copernicus-0.0.2.dist-info/RECORD
